artgen/__init__.py
artgen/cli.py
artgen/img.py
artgen/interactive_cli.py
artgen/interactive_web.py
artgen/templates/index.html
artgen-0.2.0.dist-info/METADATA
artgen-0.2.0.dist-info/WHEEL
artgen-0.2.0.dist-info/entry_points.txt
artgen-0.2.0.dist-info/RECORD
